dart.py
dart-1.0.dist-info/DESCRIPTION.rst
dart-1.0.dist-info/METADATA
dart-1.0.dist-info/metadata.json
dart-1.0.dist-info/RECORD
dart-1.0.dist-info/top_level.txt
dart-1.0.dist-info/WHEEL
