Metadata-Version: 1.0
Name: dart
Version: 1.0
Summary: Turn URL variables into models.
Home-page: https://github.com/landakram/dart
Author: Mark Hudnall
Author-email: me@markhudnall.com
License: MIT
Platform: UNKNOWN
